identity_trace/__init__.py
identity_trace/__main__.py
identity_trace/config.py
identity_trace/constants.py
identity_trace/decorator.py
identity_trace/logger.py
identity_trace/matcher.py
identity_trace/orchestration.py
identity_trace/registry.py
identity_trace/runner.py
identity_trace/test_runner.py
identity_trace/tracer.py
identity_trace/utils.py
identity_trace/wrappers.py
identity_trace_python_agent-1.0.14.dist-info/METADATA
identity_trace_python_agent-1.0.14.dist-info/WHEEL
identity_trace_python_agent-1.0.14.dist-info/top_level.txt
identity_trace_python_agent-1.0.14.dist-info/RECORD
